{
    "nctId": "NCT01177891",
    "title": "Genetic Analysis of Familial Cases of Premature Ovarian Failure",
    "symPyJSON": {
        "type": "and",
        "operands": [
            {
                "type": "and",
                "operands": [
                    {
                        "type": "and",
                        "operands": [
                            {
                                "type": "variable",
                                "value": "Female subjects between 16 and 40 years"
                            },
                            {
                                "type": "variable",
                                "value": "women older than 40 years with a cessation of ovarian function before the age of 40 years with increased levels of FSH"
                            }
                        ]
                    },
                    {
                        "type": "and",
                        "operands": [
                            {
                                "type": "variable",
                                "value": "Primary or secondary amenorrhea for more than three months with LH and FSH > 30mUI/ml"
                            },
                            {
                                "type": "not",
                                "operands": [
                                    {
                                        "type": "or",
                                        "operands": [
                                            {
                                                "type": "variable",
                                                "value": "cases of fragile X syndrome in the family"
                                            },
                                            {
                                                "type": "variable",
                                                "value": "cases of blepharophimosis syndrome in the family"
                                            }
                                        ]
                                    }
                                ]
                            }
                        ]
                    },
                    {
                        "type": "and",
                        "operands": [
                            {
                                "type": "variable",
                                "value": "At least two cases in the family"
                            },
                            {
                                "type": "variable",
                                "value": "Origin Caucasian"
                            },
                            {
                                "type": "variable",
                                "value": "Patient signing the consent form for at least the blood sample"
                            },
                            {
                                "type": "variable",
                                "value": "Patient with Social Security"
                            }
                        ]
                    }
                ]
            },
            {
                "type": "or",
                "operands": [
                    {
                        "type": "and",
                        "operands": [
                            {
                                "type": "variable",
                                "value": "The presence of cycles until the age of 40 years with proven fertility, at least one child"
                            },
                            {
                                "type": "variable",
                                "value": "Amenorrhea and FSH > 30mUI/ml according to the criteria of the index subject"
                            },
                            {
                                "type": "variable",
                                "value": "Men of the family of index case"
                            }
                        ]
                    },
                    {
                        "type": "and",
                        "operands": [
                            {
                                "type": "variable",
                                "value": "Women of Caucasian origin"
                            },
                            {
                                "type": "variable",
                                "value": "Women who had regular cycles until at least age 40 and at least one child"
                            },
                            {
                                "type": "not",
                                "operands": [
                                    {
                                        "type": "variable",
                                        "value": "history of thyroid disease or diabetes type 1"
                                    }
                                ]
                            },
                            {
                                "type": "variable",
                                "value": "Woman signing the consent form for at least the blood sample"
                            },
                            {
                                "type": "variable",
                                "value": "Must have minimum age of 16 Years"
                            }
                        ]
                    }
                ]
            },
            {
                "type": "not",
                "operands": [
                    {
                        "type": "or",
                        "operands": [
                            {
                                "type": "variable",
                                "value": "Blood donation of more than 450ml in the previous three months"
                            },
                            {
                                "type": "variable",
                                "value": "Subject with an abnormal karyotype in favor of Turner syndrome or having a premutation of the FMR1 gene or a syndromic form"
                            },
                            {
                                "type": "variable",
                                "value": "Subject exclusion period in another study without direct individual benefit"
                            },
                            {
                                "type": "variable",
                                "value": "Subject refusing to sign the consent form"
                            }
                        ]
                    }
                ]
            }
        ]
    },
    "symPyExpression": "And(Symbol('At least two cases in the family'), Symbol('Female subjects between 16 and 40 years'), Symbol('Origin Caucasian'), Symbol('Patient signing the consent form for at least the blood sample'), Symbol('Patient with Social Security'), Symbol('Primary or secondary amenorrhea for more than three months with LH and FSH > 30mUI/ml'), Symbol('women older than 40 years with a cessation of ovarian function before the age of 40 years with increased levels of FSH'), Not(Or(Symbol('cases of blepharophimosis syndrome in the family'), Symbol('cases of fragile X syndrome in the family'))), Not(Or(Symbol('Blood donation of more than 450ml in the previous three months'), Symbol('Subject exclusion period in another study without direct individual benefit'), Symbol('Subject refusing to sign the consent form'), Symbol('Subject with an abnormal karyotype in favor of Turner syndrome or having a premutation of the FMR1 gene or a syndromic form'))), Or(And(Symbol('Amenorrhea and FSH > 30mUI/ml according to the criteria of the index subject'), Symbol('Men of the family of index case'), Symbol('The presence of cycles until the age of 40 years with proven fertility, at least one child')), And(Symbol('Must have minimum age of 16 Years'), Symbol('Woman signing the consent form for at least the blood sample'), Symbol('Women of Caucasian origin'), Symbol('Women who had regular cycles until at least age 40 and at least one child'), Not(Symbol('history of thyroid disease or diabetes type 1')))))"
}