{
    "nct_id": "NCT05912231",
    "official_title": "Proton Versus Photon Ultrahypofractionated Radiation Therapy and Its Impact on Normal Tissue",
    "inclusion_criteria": "* ≥18 years of age\n* Non-metastatic Breast Cancer patients who are scheduled to receive conventional left-sided or bilateral breast/chest wall RT inclusive of treatment to the internal mammary lymph nodes (IMNs)\n* Prior chemotherapy is permitted\n* Ability to understand and the willingness to sign a written informed consent document\n* No contraindication to MRI\n* Patients with right-sided breast cancer or patients with left-sided patients not requiring treatment to the IMNs, but where cardiac anatomy is determined to be unfavorable by the study PI, will be considered eligible.\nHealthy volunteers allowed\nMust be FEMALE\nMust have minimum age of 18 Years",
    "exclusion_criteria": "* Person who is pregnant or breastfeeding.\n* Patients receiving any other investigational agent will not be excluded from study eligibility, unless the patient is already enrolled in an interventional study evaluating cardiac toxicity. No cytotoxic therapy or radiotherapy may be used during radiation therapy.\n* Contra-indication to gadolinium contrast (e.g., chronic kidney disease)\n* Contra-indication to radiotherapy (e.g., scleroderma, p53 mutation)",
    "miscellaneous_criteria": ""
}